phsp.py
phsp-0.1.dist-info/WHEEL
phsp-0.1.dist-info/METADATA
phsp-0.1.dist-info/RECORD
