Metadata-Version: 2.1
Name: phsp
Version: 0.1
Summary: phsp: a great simple useless project
Home-page: https://github.com/phsilva/ph-sample-package
License: UNKNOWN
Author: Paulo Henrique Silva
Author-email: ph.silva@gmail.com
